{
  "uid": "325864133",
  "name": "飞天闪客",
  "space_url": "https://space.bilibili.com/325864133",
  "total": 70,
  "series_count": 12,
  "series": {
    "闪客": 32,
    "一飞冲天": 5,
    "未分类 / 其他": 24,
    "白话Transformer02": 1,
    "白话Transformer01": 1,
    "AI入门07": 1,
    "AI入门06": 1,
    "AI入门05": 1,
    "AI入门04": 1,
    "AI入门03": 1,
    "AI入门02": 1,
    "AI入门01": 1
  },
  "exported_at": "2026-07-22T13:43:18.585586+00:00",
  "tool": "loop-bilibili",
  "module": "catalog",
  "profile": "conservative"
}
